[
  {"word": "Покриття", "description": "Шлях по боці дороги, призначений для пішоходів.", "category": "Вулиця", "complexity": "Easy"},
  {"word": "Пішохідний перехід", "isPro" : "false", "description": "Відмічена частина дороги, де пішоходи мають право переходити.", "category": "Вулиця", "complexity": "Easy"},
  {"word": "Провулок", "isPro" : "false", "description": "Вузька дорога або стежка між будівлями.", "category": "Вулиця", "complexity": "Easy"},
  {"word": "Бульвар", "description": "Широка вулиця в місті або місті, часто з деревами.", "category": "Вулиця", "complexity": "Medium"},
  {"word": "Перехрестя", "description": "Місце, де перетинаються дві або більше вулиць.", "category": "Вулиця", "complexity": "Medium"},
  {"word": "Кільцеве перехрестя", "isPro" : "false", "description": "Кругове місце, де дороги зустрічаються і транспорт повинен об'їжджати центральний острів.", "category": "Вулиця", "complexity": "Medium"},
  {"word": "Бруківка", "description": "Маленький, круглий камінь, що використовується для покриття дорожньої поверхні.", "category": "Вулиця", "complexity": "Medium"},
  {"word": "Авеню", "isPro" : "false", "description": "Широка вулиця в місті або місті, зазвичай з деревами через рівні інтервали по обидва боки.", "category": "Вулиця", "complexity": "Medium"},
  {"word": "Тупик", "description": "Вулиця з одним в'їздом та виїздом, що закінчується кільцем.", "category": "Вулиця", "complexity": "Hard"},
  {"word": "Еспланада", "description": "Широка та відкрита простора площа перед замком, палацом або фортецею.", "category": "Вулиця", "complexity": "Hard"},
  {"word": "Автострада", "description": "Широка дорога для швидкого руху транспорту, без можливості переходу пішоходів.", "category": "Вулиця", "complexity": "Hard"},
  {"word": "Променад", "description": "Пішохідна прогулянка або спеціальна зона для пішохідних прогулянок містом.", "category": "Вулиця", "complexity": "Hard"}
  ]